yet_another_retry/__init__.py
yet_another_retry/__main__.py
yet_another_retry/api.py
yet_another_retry/exception_handlers/__init__.py
yet_another_retry/exception_handlers/default_exception_handler.py
yet_another_retry/retry_handlers/__init__.py
yet_another_retry/retry_handlers/default_retry_handler.py
yet_another_retry/retry_handlers/exponential_backoff.py
yet_another_retry/retry_handlers/sleep_attempt_seconds.py
yet_another_retry-1.0.1.dist-info/METADATA
yet_another_retry-1.0.1.dist-info/WHEEL
yet_another_retry-1.0.1.dist-info/entry_points.txt
yet_another_retry-1.0.1.dist-info/licenses/LICENSE
yet_another_retry-1.0.1.dist-info/RECORD
