Metadata-Version: 2.4
Name: yet-another-retry
Version: 1.0.1
Summary: Yet another retry decorator for Python
Project-URL: Homepage, https://github.com/MazrimT/yet-another-retry
Project-URL: Repository, https://github.com/MazrimT/yet-another-retry.git
Project-URL: Issues, https://github.com/MazrimT/yet-another-retry/issues
Author: MazrimT
License: MIT License
License-File: LICENSE
Keywords: decorator,retry,retry decorator
Classifier: Development Status :: 5 - Production/Stable
Classifier: Programming Language :: Python :: 3
Classifier: Programming Language :: Python :: 3.9
Classifier: Programming Language :: Python :: 3.10
Classifier: Programming Language :: Python :: 3.11
Classifier: Programming Language :: Python :: 3.12
Classifier: Programming Language :: Python :: 3.13
Classifier: Topic :: Software Development
Requires-Python: >=3.10
